botato/__init__.py
botato/client.py
botato/data/intents.json
botato/gateway/__init__.py
botato/gateway/connection.py
botato/gateway/events.py
botato/http/__init__.py
botato/http/client.py
botato/http/routes.py
botato/intents.py
botato/models/__init__.py
botato/models/base.py
botato/models/channel.py
botato/models/embed.py
botato/models/emoji.py
botato/models/guild.py
botato/models/interaction.py
botato/models/member.py
botato/models/message.py
botato/models/reaction.py
botato/models/role.py
botato/models/snowflake.py
botato/models/user.py
botato/utils/__init__.py
botato/utils/logger.py
botato-0.1.1.dist-info/LICENSE
botato-0.1.1.dist-info/METADATA
botato-0.1.1.dist-info/WHEEL
botato-0.1.1.dist-info/RECORD
