Metadata-Version: 2.3
Name: botato
Version: 0.1.1
Summary: A modern and maintainable Discord bot framework for Python.
License: GPL-3.0
Keywords: discord,bot,framework,python,asyncio
Author: Shiv
Author-email: shiv@zerobytes.fr
Requires-Python: >=3.13,<4.0
Classifier: Development Status :: 3 - Alpha
Classifier: Framework :: AsyncIO
Classifier: Intended Audience :: Developers
Classifier: License :: OSI Approved :: GNU General Public License v3 (GPLv3)
Classifier: Operating System :: OS Independent
Classifier: Programming Language :: Python :: 3
Classifier: Programming Language :: Python :: 3.13
Classifier: Topic :: Software Development :: Libraries
Requires-Dist: aiohttp (>=3.11.18,<4.0.0)
Requires-Dist: aiolimiter (>=1.2,<2.0)
Requires-Dist: loguru (>=0.7.0,<0.8.0)
Requires-Dist: pydantic (>=2.11,<3.0)
Requires-Dist: python-dotenv (>=1.1.0,<2.0.0)
Requires-Dist: websockets (>=15.0,<16.0)
Project-URL: Repository, https://github.com/shivkun/botato
Project-URL: documentation, https://shivkun.github.io/botato
Project-URL: homepage, https://github.com/shivkun/botato
Project-URL: issues, https://github.com/shivkun/botato/issues
